django_tables2_column_shifter/__init__.py
django_tables2_column_shifter/tables.py
django_tables2_column_shifter/locale/el/LC_MESSAGES/django.mo
django_tables2_column_shifter/locale/el/LC_MESSAGES/django.po
django_tables2_column_shifter/locale/pl/LC_MESSAGES/django.mo
django_tables2_column_shifter/locale/pl/LC_MESSAGES/django.po
django_tables2_column_shifter/locale/pt_BR/LC_MESSAGES/django.mo
django_tables2_column_shifter/locale/pt_BR/LC_MESSAGES/django.po
django_tables2_column_shifter/static/django_tables2_column_shifter/img/check.png
django_tables2_column_shifter/static/django_tables2_column_shifter/img/cols.png
django_tables2_column_shifter/static/django_tables2_column_shifter/img/loader.gif
django_tables2_column_shifter/static/django_tables2_column_shifter/img/uncheck.png
django_tables2_column_shifter/static/django_tables2_column_shifter/js/django_tables2_column_shifter.js
django_tables2_column_shifter/static/django_tables2_column_shifter/js/django_tables2_column_shifter.min.js
django_tables2_column_shifter/templates/django_tables2_column_shifter/bootstrap2.html
django_tables2_column_shifter/templates/django_tables2_column_shifter/bootstrap3.html
django_tables2_column_shifter/templates/django_tables2_column_shifter/bootstrap4-responsive.html
django_tables2_column_shifter/templates/django_tables2_column_shifter/bootstrap4.html
django_tables2_column_shifter/templates/django_tables2_column_shifter/bootstrap5-responsive.html
django_tables2_column_shifter/templates/django_tables2_column_shifter/bootstrap5.html
django_tables2_column_shifter/templates/django_tables2_column_shifter/table.html
django_tables2_column_shifter/templates/django_tables2_column_shifter/_partials/bootstrap4_table_block.html
django_tables2_column_shifter/templates/django_tables2_column_shifter/_partials/bootstrap5_table_block.html
django_tables2_column_shifter/tests/__init__.py
django_tables2_column_shifter/tests/models.py
django_tables2_column_shifter/tests/settings.py
django_tables2_column_shifter-2.2.0.dist-info/LICENSE
django_tables2_column_shifter-2.2.0.dist-info/METADATA
django_tables2_column_shifter-2.2.0.dist-info/WHEEL
django_tables2_column_shifter-2.2.0.dist-info/top_level.txt
django_tables2_column_shifter-2.2.0.dist-info/RECORD
