Metadata-Version: 2.1
Name: django-tables2-column-shifter
Version: 2.2.0
Summary: Extension for django_tables2 can dynamically show or hide columns
Home-page: https://github.com/djk2/django-tables2-column-shifter
Author: Grzegorz Tężycki
Author-email: grzegorz.tezycki@gmail.com
License: BSD
Keywords: django_tables2 django columns
Classifier: Environment :: Web Environment
Classifier: Framework :: Django
Classifier: License :: OSI Approved :: BSD License
Classifier: Operating System :: OS Independent
Classifier: Programming Language :: Python
Classifier: Programming Language :: Python :: 2
Classifier: Programming Language :: Python :: 2.7
Classifier: Programming Language :: Python :: 3
Classifier: Programming Language :: Python :: 3.6
Classifier: Programming Language :: Python :: 3.8
Classifier: Topic :: Utilities
License-File: LICENSE
Requires-Dist: Django (>=1.9)
Requires-Dist: django-tables2 (>=1.5.0)
